mbclib/__init__.py
mbclib-0.0.2.dist-info/LICENSE
mbclib-0.0.2.dist-info/METADATA
mbclib-0.0.2.dist-info/WHEEL
mbclib-0.0.2.dist-info/top_level.txt
mbclib-0.0.2.dist-info/RECORD
