Metadata-Version: 2.1
Name: mbclib
Version: 0.0.2
Summary: A library for querying the STIX data for the MBC (Malware Behavior Catalog).
Home-page: https://github.com/accidentalrebel/mbclib
Author: Karlo Licudine
Author-email: karlolicudine@gmail.com
License: UNKNOWN
Platform: UNKNOWN
Requires-Dist: stix2
